mips32_pipelined_design.v
`timescale 1ns / 1ps
module mips32_pipeline (clk1, clk2);

  input clk1, clk2; // Two-phase clock
  reg [31:0] PC, IF_ID_IR, IF_ID_NPC;
  reg [31:0] ID_EX_IR, ID_EX_NPC, ID_EX_A, ID_EX_B, ID_EX_Imm;
  reg [2:0] ID_EX_type, EX_MEM_type, MEM_WB_type;
  reg [31:0] EX_MEM_IR, EX_MEM_ALUOut, EX_MEM_B;
  reg EX_MEM_cond;
  reg [31:0] MEM_WB_IR, MEM_WB_ALUOut, MEM_WB_LMD;

  reg [31:0] Reg [0:31]; // Register bank (32 x 32)
  reg [31:0] Mem [0:1023]; // 1024 x 32 memory

  parameter ADD=6'b000000, SUB=6'b000001, AND=6'b000010, OR=6'b000011,
            SLT=6'b000100, MUL=6'b000101, HLT=6'b111111, LW=6'b001000,
            SW=6'b001001, ADDI=6'b001010, SUBI=6'b001011,SLTI=6'b001100,
            BNEQZ=6'b001101, BEQZ=6'b001110;
  parameter RR_ALU=3'b000, RM_ALU=3'b001, LOAD=3'b010, STORE=3'b011,
            BRANCH=3'b100, HALT=3'b101;

  reg HALTED;
  // Set after HLT instruction is completed (in WB stage)
  reg TAKEN_BRANCH;
  // Required to disable instructions after branch
  
  
  always @(posedge clk1) // IF Stage
    if (HALTED == 0)
    begin
      if (((EX_MEM_IR[31:26] == BEQZ) && (EX_MEM_cond == 1)) ||
          ((EX_MEM_IR[31:26] == BNEQZ) && (EX_MEM_cond == 0)))
      begin
        IF_ID_IR <= #2 Mem[EX_MEM_ALUOut];
        TAKEN_BRANCH <= #2 1'b1;
        IF_ID_NPC <= #2 EX_MEM_ALUOut + 1;
        PC <= #2 EX_MEM_ALUOut + 1;
      end
      else
      begin
        IF_ID_IR <= #2 Mem[PC];
        IF_ID_NPC <= #2 PC + 1;
        PC <= #2 PC + 1;
      end
    end
  
  always @(posedge clk2) // ID Stage
    if (HALTED == 0)
    begin
      if (IF_ID_IR[25:21] == 5'b00000) // R0 -> Special Register, have value 0
        ID_EX_A <= 0;
      else
        ID_EX_A <= #2 Reg[IF_ID_IR[25:21]]; // "rs"
      if (IF_ID_IR[20:16] == 5'b00000)
        ID_EX_B <= 0;
      else
        ID_EX_B <= #2 Reg[IF_ID_IR[20:16]]; // "rt"
      ID_EX_NPC <= #2 IF_ID_NPC;
      ID_EX_IR <= #2 IF_ID_IR;
      ID_EX_Imm <= #2 {{16{IF_ID_IR[15]}}, {IF_ID_IR[15:0]}};
      case (IF_ID_IR[31:26])
        ADD,SUB,AND,OR,SLT,MUL:
          ID_EX_type <= #2 RR_ALU;
        ADDI,SUBI,SLTI:
          ID_EX_type <= #2 RM_ALU;
        LW:
          ID_EX_type <= #2 LOAD;
        SW:
          ID_EX_type <= #2 STORE;
        BNEQZ,BEQZ:
          ID_EX_type <= #2 BRANCH;
        HLT:
          ID_EX_type <= #2 HALT;
        default:
          ID_EX_type <= #2 HALT;
        // Invalid opcode
      endcase
    end
  
  always @(posedge clk1) // EX Stage
    if (HALTED == 0)
    begin
      EX_MEM_type <= #2 ID_EX_type;
      EX_MEM_IR <= #2 ID_EX_IR;
      TAKEN_BRANCH <= #2 0;
      case (ID_EX_type)
        RR_ALU:
        begin
          case (ID_EX_IR[31:26]) // "opcode"
            ADD:
              EX_MEM_ALUOut <= #2 ID_EX_A + ID_EX_B;
            SUB:
              EX_MEM_ALUOut <= #2 ID_EX_A - ID_EX_B;
            AND:
              EX_MEM_ALUOut <= #2 ID_EX_A & ID_EX_B;
            OR:
              EX_MEM_ALUOut <= #2 ID_EX_A | ID_EX_B;
            SLT:
              EX_MEM_ALUOut <= #2 ID_EX_A < ID_EX_B;
            MUL:
              EX_MEM_ALUOut <= #2 ID_EX_A * ID_EX_B;
            default:
              EX_MEM_ALUOut <= #2 32'hxxxxxxxx;
          endcase
        end
        RM_ALU:
        begin
          case (ID_EX_IR[31:26]) // "opcode"
            ADDI:
              EX_MEM_ALUOut <= #2 ID_EX_A + ID_EX_Imm;
            SUBI:
              EX_MEM_ALUOut <= #2 ID_EX_A - ID_EX_Imm;
            SLTI:
              EX_MEM_ALUOut <= #2 ID_EX_A < ID_EX_Imm;
            default:
              EX_MEM_ALUOut <= #2 32'hxxxxxxxx;
          endcase
        end
        LOAD, STORE:
        begin
          EX_MEM_ALUOut <= #2 ID_EX_A + ID_EX_Imm;
          EX_MEM_B <= #2 ID_EX_B;
        end
        BRANCH:
        begin
          EX_MEM_ALUOut <= #2 ID_EX_NPC + ID_EX_Imm;
          EX_MEM_cond <= #2 (ID_EX_A == 0);
        end
      endcase
    end
  
  
  always @(posedge clk2) // MEM Stage
    if (HALTED == 0)
    begin
      MEM_WB_type <= EX_MEM_type;
      MEM_WB_IR <= #2 EX_MEM_IR;
      case (EX_MEM_type)
        RR_ALU, RM_ALU:
          MEM_WB_ALUOut <= #2 EX_MEM_ALUOut;
        LOAD:
          MEM_WB_LMD <= #2 Mem[EX_MEM_ALUOut];
        STORE:
          if (TAKEN_BRANCH == 0) // Disable write
            Mem[EX_MEM_ALUOut] <= #2 EX_MEM_B;
      endcase
    end
  
  
  always @(posedge clk1) // WB Stage
  begin
    if (TAKEN_BRANCH == 0) // Disable write if branch taken
    case (MEM_WB_type)
      RR_ALU:
        Reg[MEM_WB_IR[15:11]] <= #2 MEM_WB_ALUOut; // "rd"
      RM_ALU:
        Reg[MEM_WB_IR[20:16]] <= #2 MEM_WB_ALUOut; // "rt"
      LOAD:
        Reg[MEM_WB_IR[20:16]] <= #2 MEM_WB_LMD; // "rt"
      HALT:
        HALTED <= #2 1'b1;
    endcase
  end
endmodule

testbench.v
`timescale 1ns/1ps
`include "mips32_pipelined_design.v"


  module mips32_tb;
  reg clk1, clk2;
  integer k;
  mips32_pipeline mips (clk1, clk2);
  initial
  begin
    clk1 = 0;
    clk2 = 0;
    repeat (20) // Generating two-phase clock
    begin
      #5 clk1 = 1;
      #5 clk1 = 0;
      #5 clk2 = 1;
      #5 clk2 = 0;
    end
  end
  initial
  begin
    for (k=0; k<31; k++)
      mips.Reg[k] = k;
    mips.Mem[0] = 32'h2801000a; // ADDI R1,R0,10
    mips.Mem[1] = 32'h28020014; // ADDI R2,R0,20
    mips.Mem[2] = 32'h28030019; // ADDI R3,R0,25
    mips.Mem[3] = 32'h0ce77800; // OR R7,R7,R7 -- dummy instr.
    mips.Mem[4] = 32'h0ce77800; // OR R7,R7,R7 -- dummy instr.
    mips.Mem[5] = 32'h00222000; // ADD R4,R1,R2
    mips.Mem[6] = 32'h0ce77800; // OR R7,R7,R7 -- dummy instr.
    mips.Mem[7] = 32'h00832800; // ADD R5,R4,R3
    mips.Mem[8] = 32'hfc000000; // HLT
    mips.HALTED = 0;
    mips.PC = 0;
    mips.TAKEN_BRANCH = 0;
    #280
     for (k=0; k<6; k++)
       $display ("R%1d - %2d", k, mips.Reg[k]);
  end
  initial
  begin
    $dumpfile ("mips.vcd");
    $dumpvars (0, mips32_tb);
    #300 $finish;
  end
endmodule

mips.vcd
$date
	Sat Aug 16 14:36:44 2025
$end
$version
	Icarus Verilog
$end
$timescale
	1ps
$end
$scope module mips32_tb $end
$var reg 1 ! clk1 $end
$var reg 1 " clk2 $end
$var integer 32 # k [31:0] $end
$scope module mips $end
$var wire 1 ! clk1 $end
$var wire 1 " clk2 $end
$var parameter 6 $ ADD $end
$var parameter 6 % ADDI $end
$var parameter 6 & AND $end
$var parameter 6 ' BEQZ $end
$var parameter 6 ( BNEQZ $end
$var parameter 3 ) BRANCH $end
$var parameter 3 * HALT $end
$var parameter 6 + HLT $end
$var parameter 3 , LOAD $end
$var parameter 6 - LW $end
$var parameter 6 . MUL $end
$var parameter 6 / OR $end
$var parameter 3 0 RM_ALU $end
$var parameter 3 1 RR_ALU $end
$var parameter 6 2 SLT $end
$var parameter 6 3 SLTI $end
$var parameter 3 4 STORE $end
$var parameter 6 5 SUB $end
$var parameter 6 6 SUBI $end
$var parameter 6 7 SW $end
$var reg 32 8 EX_MEM_ALUOut [31:0] $end
$var reg 32 9 EX_MEM_B [31:0] $end
$var reg 32 : EX_MEM_IR [31:0] $end
$var reg 1 ; EX_MEM_cond $end
$var reg 3 < EX_MEM_type [2:0] $end
$var reg 1 = HALTED $end
$var reg 32 > ID_EX_A [31:0] $end
$var reg 32 ? ID_EX_B [31:0] $end
$var reg 32 @ ID_EX_IR [31:0] $end
$var reg 32 A ID_EX_Imm [31:0] $end
$var reg 32 B ID_EX_NPC [31:0] $end
$var reg 3 C ID_EX_type [2:0] $end
$var reg 32 D IF_ID_IR [31:0] $end
$var reg 32 E IF_ID_NPC [31:0] $end
$var reg 32 F MEM_WB_ALUOut [31:0] $end
$var reg 32 G MEM_WB_IR [31:0] $end
$var reg 32 H MEM_WB_LMD [31:0] $end
$var reg 3 I MEM_WB_type [2:0] $end
$var reg 32 J PC [31:0] $end
$var reg 1 K TAKEN_BRANCH $end
$upscope $end
$upscope $end
$enddefinitions $end
$comment Show the parameter values. $end
$dumpall
b1001 7
b1011 6
b1 5
b11 4
b1100 3
b100 2
b0 1
b1 0
b11 /
b101 .
b1000 -
b10 ,
b111111 +
b101 *
b100 )
b1101 (
b1110 '
b10 &
b1010 %
b0 $
$end
#0
$dumpvars
0K
b0 J
bx I
bx H
bx G
bx F
bx E
bx D
bx C
bx B
bx A
bx @
bx ?
bx >
0=
bx <
x;
bx :
bx 9
bx 8
b11111 #
0"
0!
$end
#5000
1!
#7000
b1 J
b1 E
b101000000000010000000000001010 D
#10000
0!
#15000
b0 >
1"
#17000
b1 C
b1010 A
b101000000000010000000000001010 @
b1 B
b1 ?
#20000
0"
#25000
1!
#27000
b1010 8
b101000000000010000000000001010 :
b1 <
b10 J
b10 E
b101000000000100000000000010100 D
#30000
0!
#35000
b1 I
1"
#37000
b1010 F
b101000000000010000000000001010 G
b10100 A
b101000000000100000000000010100 @
b10 B
b10 ?
#40000
0"
#45000
1!
#47000
b11 J
b11 E
b101000000000110000000000011001 D
b10100 8
b101000000000100000000000010100 :
#50000
0!
#55000
1"
#57000
b11001 A
b101000000000110000000000011001 @
b11 B
b11 ?
b10100 F
b101000000000100000000000010100 G
#60000
0"
#65000
1!
#67000
b11001 8
b101000000000110000000000011001 :
b100 J
b100 E
b1100111001110111100000000000 D
#70000
0!
#75000
1"
#77000
b11001 F
b101000000000110000000000011001 G
b0 C
b111100000000000 A
b1100111001110111100000000000 @
b100 B
b111 ?
b111 >
#80000
0"
#85000
1!
#87000
b101 J
b101 E
b111 8
b1100111001110111100000000000 :
b0 <
#90000
0!
#95000
b0 I
1"
#97000
b101 B
b111 F
b1100111001110111100000000000 G
#100000
0"
#105000
1!
#107000
b110 J
b110 E
b1000100010000000000000 D
#110000
0!
#115000
1"
#117000
b10000000000000 A
b1000100010000000000000 @
b110 B
b10100 ?
b1010 >
#120000
0"
#125000
1!
#127000
b111 J
b111 E
b1100111001110111100000000000 D
b11110 8
b1000100010000000000000 :
#130000
0!
#135000
1"
#137000
b111100000000000 A
b1100111001110111100000000000 @
b111 B
b111 ?
b111 >
b11110 F
b1000100010000000000000 G
#140000
0"
#145000
1!
#147000
b111 8
b1100111001110111100000000000 :
b1000 J
b1000 E
b100000110010100000000000 D
#150000
0!
#155000
1"
#157000
b111 F
b1100111001110111100000000000 G
b10100000000000 A
b100000110010100000000000 @
b1000 B
b11001 ?
b11110 >
#160000
0"
#165000
1!
#167000
b1001 J
b1001 E
b11111100000000000000000000000000 D
b110111 8
b100000110010100000000000 :
#170000
0!
#175000
b0 ?
b0 >
1"
#177000
b101 C
b0 A
b11111100000000000000000000000000 @
b1001 B
b110111 F
b100000110010100000000000 G
#180000
0"
#185000
1!
#187000
b11111100000000000000000000000000 :
b101 <
b1010 J
b1010 E
bx D
#190000
0!
#195000
b101 I
1"
#197000
b11111100000000000000000000000000 G
bx A
bx @
b1010 B
bx ?
bx >
#200000
0"
#205000
1!
#207000
b1011 J
b1011 E
bx :
1=
#210000
0!
#215000
1"
#220000
0"
#225000
1!
#230000
0!
#235000
1"
#240000
0"
#245000
1!
#250000
0!
#255000
1"
#260000
0"
#265000
1!
#270000
0!
#275000
1"
#280000
0"
b110 #
